skencli/__init__.py
skencli/scan_runner.py
skencli/sken_runner.py
skencli/utils.py
skencli-0.1.86.dist-info/LICENSE
skencli-0.1.86.dist-info/METADATA
skencli-0.1.86.dist-info/WHEEL
skencli-0.1.86.dist-info/entry_points.txt
skencli-0.1.86.dist-info/top_level.txt
skencli-0.1.86.dist-info/RECORD
