Metadata-Version: 2.1
Name: skencli
Version: 0.1.86
Summary: Sken CLI for running scanners
Home-page: http://sken.ai/
Author: Sken.ai
Author-email: author@sken.ai
License: UNKNOWN
Platform: UNKNOWN
Classifier: Development Status :: 4 - Beta
Classifier: Environment :: Console
Classifier: Intended Audience :: Developers
Classifier: Programming Language :: Python :: 3
Classifier: Operating System :: OS Independent
Requires-Python: >=2.7
Requires-Dist: PyYAML (>=5.1.2)
Requires-Dist: boto3 (>=1.10.26)
Requires-Dist: docker (>=4.2.1)
Requires-Dist: wget (>=3.2)
Requires-Dist: requests (>=2.7.0)
